<?xml version="1.0" encoding="UTF-8"?>
<jcr:root xmlns:sling="http://sling.apache.org/jcr/sling/1.0" xmlns:cq="http://www.day.com/jcr/cq/1.0" xmlns:jcr="http://www.jcp.org/jcr/1.0" xmlns:mix="http://www.jcp.org/jcr/mix/1.0"
    jcr:primaryType="cq:Page">
    <jcr:content
        cq:contextHubPath="/etc/cloudsettings/default/contexthub"
        cq:contextHubSegmentsPath="/etc/segmentation/contexthub"
        cq:lastModified="{Date}2019-03-04T13:27:12.839Z"
        cq:lastModifiedBy="ssatheshkumar"
        cq:lastReplicated="{Date}2019-04-03T07:01:18.162Z"
        cq:lastReplicatedBy="aa"
        cq:lastReplicationAction="Activate"
        cq:lastRolledout="{Date}2019-03-04T13:27:13.608Z"
        cq:lastRolledoutBy="ssatheshkumar"
        cq:template="/apps/gaming/templates/page-player"
        jcr:isCheckedOut="{Boolean}true"
        jcr:lastModified="{Date}2018-08-06T13:45:32.917-04:00"
        jcr:mixinTypes="[cq:LiveRelationship,mix:versionable]"
        jcr:primaryType="cq:PageContent"
        jcr:title="Players"
        jcr:uuid="83d9e3c1-a924-45b3-aa1a-ce9a108e1772"
        sling:resourceType="gaming/components/structure/pageplayer"
        featurePlayer="false"
        navigationTheme="theme-dark"
        robotsOptions="noindex, nofollow"/>
    <tsvetelin-dimitrov/>
    <jacob-medina/>
    <damian-steele/>
    <vincent-cayonte/>
    <ethan-arnold/>
    <riley-taylor/>
    <robert-garcia/>
    <eoghan-oneill/>
    <ethan-yankel/>
    <seong-won-yoon/>
    <kevin-yarnell/>
    <alfonso-aguirre-rodriguez/>
    <soren_berg/>
    <jesper-svenningsen/>
    <mike-yeung/>
    <micael-rodrigues/>
    <luan-cardoso/>
    <marcelo-mello/>
    <gabriel-peixoto/>
    <bruno-farias/>
    <diogo-roge/>
    <daniel-marcon/>
    <thiago-herrera/>
    <matheus-luz/>
    <yuri-gomes/>
    <filipe-de-caires/>
    <ramon-toledo/>
    <nikola-andrews/>
    <dante-cruz/>
    <andre-dahlstrom/>
    <matthew-delisi/>
    <grant-espe/>
    <andrej-francisty/>
    <andreas-karlsson/>
    <david-osmar/>
    <david-paz/>
    <minho-park/>
    <jay-won/>
    <martin-hansen/>
    <marcin-jankowski/>
    <luka-perkovic/>
    <petter-freyschuss/>
    <kim-bae-in/>
    <alexandre-pianaro/>
    <nathan-schmitt/>
    <kenny-schrub/>
    <dan-madesclaire/>
    <oscar-canellas/>
    <cem-bolukbasi/>
    <danny-engels/>
    <seung-tae-choi/>
    <jae-hui-hong/>
    <janghyun-hwang/>
    <hyeon-woo-jo/>
    <won-sik-jung/>
    <ji-hyeok-kim/>
    <jong-seok-kim/>
    <jun-ho-kim/>
    <dong-eun-lee/>
    <jun-young-park/>
    <seung-hyun-seong/>
    <brandon-holand/>
    <samual-broadley/>
    <simon-papamarkos/>
    <bryce-paule/>
    <quin-korebrits/>
    <michael-hall/>
    <tyler-reilly/>
    <josh-potter/>
    <liam-schembri/>
    <alistair-johnson/>
    <yan-junze/>
    <li-yuanhao/>
    <liu-shiyu/>
    <jian-zihao/>
    <shi-senming/>
    <liu-zhihao/>
    <hong-haoxuan/>
    <dai-zhichun/>
    <richard-papillon/>
    <feb14_team/>
    <techm_player1/>
    <techm_player2/>
    <techm_player3/>
    <techm_player4/>
    <_x0032_/>
    <mb/>
    <manju/>
    <guru/>
    <alpha_test/>
    <player-rajesh/>
    <player_test1/>
    <hong-haoxuan1/>
    <tsvetelin-dimitrov_msm_moved/>
    <player-rajesh_msm_moved/>
    <test_player1/>
    <player_test3/>
    <player_test2/>
    <gamautm-116_sametab/>
    <test-player1/>
    <test-player10/>
    <social-links/>
    <test-player/>
    <player1/>
</jcr:root>
